pylint_protobuf/__init__.py
pylint_protobuf/parse_proto.py
pylint_protobuf/transform.py
pylint_protobuf-0.21.0.dist-info/AUTHORS.md
pylint_protobuf-0.21.0.dist-info/LICENSE
pylint_protobuf-0.21.0.dist-info/METADATA
pylint_protobuf-0.21.0.dist-info/WHEEL
pylint_protobuf-0.21.0.dist-info/top_level.txt
pylint_protobuf-0.21.0.dist-info/RECORD
