Metadata-Version: 2.1
Name: pylint-protobuf
Version: 0.21.0
Summary: A plugin for making Pylint aware of the fields of protobuf-generated classes
Home-page: https://github.com/nelfin/pylint-protobuf
Author: Andrew Haigh
Author-email: hello@nelf.in
License: MIT
Keywords: pylint,plugin,protobuf
Platform: UNKNOWN
Classifier: Development Status :: 4 - Beta
Classifier: Programming Language :: Python :: 3
Classifier: Environment :: Console
Classifier: License :: OSI Approved :: MIT License
Classifier: Intended Audience :: Developers
Classifier: Topic :: Software Development :: Quality Assurance
Requires-Dist: astroid
Requires-Dist: pylint
Requires-Dist: protobuf
